[{"cid": 85837198, "sum_user_true_count": 153, "sum_user_error_count": 21, "sum_comment_true_count": 313, "sum_comment_error_count": 0, "execute_duration": "88s"}, {"cid": 72614347, "sum_user_true_count": 18, "sum_user_error_count": 21, "sum_comment_true_count": 1000, "sum_comment_error_count": 0, "execute_duration": "294s"}, {"cid": 86520166, "sum_user_true_count": 259, "sum_user_error_count": 23, "sum_comment_true_count": 500, "sum_comment_error_count": 0, "execute_duration": "138s"}, {"cid": 86102526, "sum_user_true_count": 316, "sum_user_error_count": 21, "sum_comment_true_count": 500, "sum_comment_error_count": 0, "execute_duration": "142s"}, {"cid": 84619899, "sum_user_true_count": 201, "sum_user_error_count": 19, "sum_comment_true_count": 300, "sum_comment_error_count": 0, "execute_duration": "93s"}, {"cid": 79038512, "sum_user_true_count": 765, "sum_user_error_count": 37, "sum_comment_true_count": 1000, "sum_comment_error_count": 0, "execute_duration": "281s"}, {"cid": 85742130, "sum_user_true_count": 260, "sum_user_error_count": 21, "sum_comment_true_count": 500, "sum_comment_error_count": 0, "execute_duration": "157s"}, {"cid": 85973025, "sum_user_true_count": 70, "sum_user_error_count": 0, "sum_comment_true_count": 100, "sum_comment_error_count": 0, "execute_duration": "28s"}, {"cid": 83562278, "sum_user_true_count": 324, "sum_user_error_count": 18, "sum_comment_true_count": 500, "sum_comment_error_count": 0, "execute_duration": "139s"}, {"cid": 81166055, "sum_user_true_count": 594, "sum_user_error_count": 41, "sum_comment_true_count": 1000, "sum_comment_error_count": 0, "execute_duration": "270s"}, {"cid": 67972178, "sum_user_true_count": 215, "sum_user_error_count": 0, "sum_comment_true_count": 300, "sum_comment_error_count": 0, "execute_duration": "83s"}, {"cid": 53527108, "sum_user_true_count": 6, "sum_user_error_count": 322, "sum_comment_true_count": 8000, "sum_comment_error_count": 0, "execute_duration": "2344s"}, {"cid": 79461548, "sum_user_true_count": 769, "sum_user_error_count": 41, "sum_comment_true_count": 1500, "sum_comment_error_count": 0, "execute_duration": "425s"}, {"cid": 82795717, "sum_user_true_count": 87, "sum_user_error_count": 0, "sum_comment_true_count": 272, "sum_comment_error_count": 0, "execute_duration": "87s"}, {"cid": 85674975, "sum_user_true_count": 264, "sum_user_error_count": 21, "sum_comment_true_count": 500, "sum_comment_error_count": 0, "execute_duration": "151s"}]