[{"cid": 70467880, "sum_user_true_count": 476, "sum_user_error_count": 34, "sum_comment_true_count": 1000, "sum_comment_error_count": 0, "execute_duration": "285s"}, {"cid": 35832220, "sum_user_true_count": 178, "sum_user_error_count": 18, "sum_comment_true_count": 653, "sum_comment_error_count": 0, "execute_duration": "189s"}, {"cid": 38681858, "sum_user_true_count": 11, "sum_user_error_count": 0, "sum_comment_true_count": 107, "sum_comment_error_count": 0, "execute_duration": "31s"}, {"cid": 86566243, "sum_user_true_count": 232, "sum_user_error_count": 21, "sum_comment_true_count": 500, "sum_comment_error_count": 0, "execute_duration": "146s"}, {"cid": 41519752, "sum_user_true_count": 312, "sum_user_error_count": 59, "sum_comment_true_count": 1500, "sum_comment_error_count": 0, "execute_duration": "434s"}, {"cid": 30629183, "sum_user_true_count": 169, "sum_user_error_count": 17, "sum_comment_true_count": 500, "sum_comment_error_count": 0, "execute_duration": "151s"}, {"cid": 86574854, "sum_user_true_count": 170, "sum_user_error_count": 0, "sum_comment_true_count": 300, "sum_comment_error_count": 0, "execute_duration": "88s"}, {"cid": 36338960, "sum_user_true_count": 591, "sum_user_error_count": 120, "sum_comment_true_count": 3000, "sum_comment_error_count": 0, "execute_duration": "851s"}, {"cid": 73349560, "sum_user_true_count": 63, "sum_user_error_count": 98, "sum_comment_true_count": 3000, "sum_comment_error_count": 0, "execute_duration": "857s"}, {"cid": 81231068, "sum_user_true_count": 126, "sum_user_error_count": 144, "sum_comment_true_count": 473, "sum_comment_error_count": 0, "execute_duration": "135s"}, {"cid": 40809684, "sum_user_true_count": 284, "sum_user_error_count": 82, "sum_comment_true_count": 2337, "sum_comment_error_count": 0, "execute_duration": "666s"}, {"cid": 86681716, "sum_user_true_count": 618, "sum_user_error_count": 41, "sum_comment_true_count": 1000, "sum_comment_error_count": 0, "execute_duration": "286s"}, {"cid": 70337101, "sum_user_true_count": 357, "sum_user_error_count": 38, "sum_comment_true_count": 1000, "sum_comment_error_count": 0, "execute_duration": "285s"}, {"cid": 32822943, "sum_user_true_count": 468, "sum_user_error_count": 41, "sum_comment_true_count": 956, "sum_comment_error_count": 0, "execute_duration": "277s"}, {"cid": 78775078, "sum_user_true_count": 497, "sum_user_error_count": 37, "sum_comment_true_count": 967, "sum_comment_error_count": 0, "execute_duration": "276s"}]